{
  "page_type": "questions",
  "chapter_number": null,
  "chapter_title": "Inserting the Missing Character",
  "passages": [],
  "questions": [
    {
      "number": 5,
      "passage_index": null,
      "seq_in_passage": null,
      "subject": "non_verbal",
      "topic_code": "missing_character",
      "topic_name": "Missing Character",
      "subtopic_code": "table_pattern",
      "subtopic_name": "Table Pattern",
      "body": "Find the missing character in the table with S, X, O in top row and 19, 24, ? in bottom row",
      "choices": {
        "a": "25",
        "b": "17",
        "c": "30",
        "d": "26"
      },
      "correct": null,
      "has_figure": true,
      "skip_reason": null
    },
    {
      "number": 6,
      "passage_index": null,
      "seq_in_passage": null,
      "subject": "non_verbal",
      "topic_code": "missing_character",
      "topic_name": "Missing Character",
      "subtopic_code": "table_pattern",
      "subtopic_name": "Table Pattern",
      "body": "Find the missing character in the table with letters B, J, Q, E, ? and numbers 2, 10, 17, 7, 8",
      "choices": {
        "a": "H and 5",
        "b": "F and 6",
        "c": "H and 6",
        "d": "5 and H"
      },
      "correct": null,
      "has_figure": true,
      "skip_reason": null
    },
    {
      "number": 7,
      "passage_index": null,
      "seq_in_passage": null,
      "subject": "non_verbal",
      "topic_code": "missing_character",
      "topic_name": "Missing Character",
      "subtopic_code": "table_pattern",
      "subtopic_name": "Table Pattern",
      "body": "Find the missing character in the table with A, 22, I, 12, ? in top row and 26, E, 18, O, ? in bottom row",
      "choices": {
        "a": "13/P",
        "b": "15/Q",
        "c": "U/6",
        "d": "6/U"
      },
      "correct": null,
      "has_figure": true,
      "skip_reason": null
    },
    {
      "number": 8,
      "passage_index": null,
      "seq_in_passage": null,
      "subject": "non_verbal",
      "topic_code": "missing_character",
      "topic_name": "Missing Character",
      "subtopic_code": "triangle_pattern",
      "subtopic_name": "Triangle Pattern",
      "body": "Find the missing character in the triangular pattern with various letters and numbers",
      "choices": {
        "a": "15/R",
        "b": "4/W",
        "c": "5/11",
        "d": "4/X"
      },
      "correct": null,
      "has_figure": true,
      "skip_reason": null
    },
    {
      "number": 9,
      "passage_index": null,
      "seq_in_passage": null,
      "subject": "non_verbal",
      "topic_code": "missing_character",
      "topic_name": "Missing Character",
      "subtopic_code": "rectangular_pattern",
      "subtopic_name": "Rectangular Pattern",
      "body": "Find the missing character in the rectangular pattern with P, 18, T, 22, ? and 16, R, 20, V, ?",
      "choices": {
        "a": "U/15",
        "b": "W/23",
        "c": "X/24",
        "d": "W/24"
      },
      "correct": null,
      "has_figure": true,
      "skip_reason": null
    },
    {
      "number": 10,
      "passage_index": null,
      "seq_in_passage": null,
      "subject": "non_verbal",
      "topic_code": "missing_character",
      "topic_name": "Missing Character",
      "subtopic_code": "quadrilateral_pattern",
      "subtopic_name": "Quadrilateral Pattern",
      "body": "Find the missing character in the pattern with 1, D, 9, ? and A, 4, I, ?",
      "choices": {
        "a": "J/10",
        "b": "M/13",
        "c": "P/16",
        "d": "P/11"
      },
      "correct": null,
      "has_figure": true,
      "skip_reason": null
    },
    {
      "number": 11,
      "passage_index": null,
      "seq_in_passage": null,
      "subject": "non_verbal",
      "topic_code": "missing_character",
      "topic_name": "Missing Character",
      "subtopic_code": "letter_arrangement",
      "subtopic_name": "Letter Arrangement",
      "body": "Find the missing character in the arrangement W, T, Q, N, K, ?, E, B",
      "choices": {
        "a": "H",
        "b": "L",
        "c": "G",
        "d": "F"
      },
      "correct": null,
      "has_figure": true,
      "skip_reason": null
    },
    {
      "number": 12,
      "passage_index": null,
      "seq_in_passage": null,
      "subject": "non_verbal",
      "topic_code": "missing_character",
      "topic_name": "Missing Character",
      "subtopic_code": "table_pattern",
      "subtopic_name": "Table Pattern",
      "body": "Find the missing character in the table with D, M, V in top row, F, P, Z in middle row, and H, S, ? in bottom row",
      "choices": {
        "a": "D",
        "b": "C",
        "c": "I",
        "d": "G",
        "e": "K"
      },
      "correct": null,
      "has_figure": true,
      "skip_reason": null
    },
    {
      "number": 13,
      "passage_index": null,
      "seq_in_passage": null,
      "subject": "non_verbal",
      "topic_code": "missing_character",
      "topic_name": "Missing Character",
      "subtopic_code": "circular_pattern",
      "subtopic_name": "Circular Pattern",
      "body": "Find the missing character in the circular pattern",
      "choices": {
        "a": "Z",
        "b": "X",
        "c": "I",
        "d": "D"
      },
      "correct": null,
      "has_figure": true,
      "skip_reason": null
    },
    {
      "number": 14,
      "passage_index": null,
      "seq_in_passage": null,
      "subject": "non_verbal",
      "topic_code": "missing_character",
      "topic_name": "Missing Character",
      "subtopic_code": "table_pattern",
      "subtopic_name": "Table Pattern",
      "body": "Find the missing character in the table with A, D, H in top row, F, I, M in middle row, and ?, N, R in bottom row",
      "choices": {
        "a": "K",
        "b": "N",
        "c": "O",
        "d": "P"
      },
      "correct": null,
      "has_figure": true,
      "skip_reason": null
    },
    {
      "number": 15,
      "passage_index": null,
      "seq_in_passage": null,
      "subject": "non_verbal",
      "topic_code": "missing_character",
      "topic_name": "Missing Character",
      "subtopic_code": "table_pattern",
      "subtopic_name": "Table Pattern",
      "body": "Find the missing character in the table with H, C, ? in top row, B, F, E in middle row, and P, R, T in bottom row",
      "choices": {
        "a": "Y",
        "b": "O",
        "c": "D",
        "d": "G"
      },
      "correct": null,
      "has_figure": true,
      "skip_reason": null
    },
    {
      "number": 16,
      "passage_index": null,
      "seq_in_passage": null,
      "subject": "non_verbal",
      "topic_code": "missing_character",
      "topic_name": "Missing Character",
      "subtopic_code": "table_pattern",
      "subtopic_name": "Table Pattern",
      "body": "Find the missing character in the table with F, I, O in top row, A, J, K in middle row, and E, M, ? in bottom row",
      "choices": {
        "a": "P",
        "b": "R",
        "c": "S",
        "d": "V"
      },
      "correct": null,
      "has_figure": true,
      "skip_reason": null
    },
    {
      "number": 17,
      "passage_index": null,
      "seq_in_passage": null,
      "subject": "non_verbal",
      "topic_code": "missing_character",
      "topic_name": "Missing Character",
      "subtopic_code": "table_pattern",
      "subtopic_name": "Table Pattern",
      "body": "Find the missing character in the table with AZ, BY, CX in top row, DW, EV, FU in middle row, and GT, ?, IR in bottom row",
      "choices": {
        "a": "HR",
        "b": "HS",
        "c": "HV",
        "d": "HU"
      },
      "correct": null,
      "has_figure": true,
      "skip_reason": null
    },
    {
      "number": 18,
      "passage_index": null,
      "seq_in_passage": null,
      "subject": "non_verbal",
      "topic_code": "missing_character",
      "topic_name": "Missing Character",
      "subtopic_code": "table_pattern",
      "subtopic_name": "Table Pattern",
      "body": "Find the missing character in the table with A, M, B, N in top row, R, C, S, D in middle row, and E, U, F, ? in bottom row",
      "choices": {
        "a": "G",
        "b": "R",
        "c": "T",
        "d": "V"
      },
      "correct": null,
      "has_figure": true,
      "skip_reason": null
    },
    {
      "number": 19,
      "passage_index": null,
      "seq_in_passage": null,
      "subject": "non_verbal",
      "topic_code": "missing_character",
      "topic_name": "Missing Character",
      "subtopic_code": "circular_pattern",
      "subtopic_name": "Circular Pattern",
      "body": "Find the missing character in the circular pattern",
      "choices": {
        "a": "G",
        "b": "U",
        "c": "V",
        "d": "H"
      },
      "correct": null,
      "has_figure": true,
      "skip_reason": null
    }
  ],
  "solutions": [],
  "answers": [],
  "_page": 276
}