{
  "page_type": "questions",
  "chapter_number": null,
  "chapter_title": null,
  "passages": [
    {
      "passage_text": "Directions (Q. Nos. 44-46) Read the following information carefully to answer the questions that follow. A family consists of six members P, Q, R, X, Y and Z. Q is the son of R but R is not the mother of Q. P and R are married couple. Y is the brother of R. X is the daughter of P and Z is the brother of P.",
      "has_figure": false,
      "topic_code": "blood_relations"
    }
  ],
  "questions": [
    {
      "number": 30,
      "passage_index": null,
      "seq_in_passage": null,
      "subject": "verbal",
      "topic_code": "blood_relations",
      "topic_name": "Blood Relations",
      "subtopic_code": "family_relationships",
      "subtopic_name": "Family Relationships",
      "body": "Pinky, who is Victor's daughter, say to Lucy, \"Your mother Rosy is the younger sister of may father, who is the third child of Joseph\". How is Joseph related to Lucy?",
      "choices": {
        "a": "Father-in-law",
        "b": "Father",
        "c": "Maternal uncle",
        "d": "Grandfather"
      },
      "correct": null,
      "has_figure": false,
      "skip_reason": null
    },
    {
      "number": 31,
      "passage_index": null,
      "seq_in_passage": null,
      "subject": "verbal",
      "topic_code": "blood_relations",
      "topic_name": "Blood Relations",
      "subtopic_code": "family_relationships",
      "subtopic_name": "Family Relationships",
      "body": "Sohan said to Mohan, \"This girl is the wife of the grandson of my mother\". How is Sohan related to this girl?",
      "choices": {
        "a": "Grandfather",
        "b": "Father",
        "c": "Husband",
        "d": "Father-in-law"
      },
      "correct": null,
      "has_figure": false,
      "skip_reason": null
    },
    {
      "number": 32,
      "passage_index": null,
      "seq_in_passage": null,
      "subject": "verbal",
      "topic_code": "blood_relations",
      "topic_name": "Blood Relations",
      "subtopic_code": "family_relationships",
      "subtopic_name": "Family Relationships",
      "body": "P's father is Q's son. M is the paternal uncle of P and N is the brother of Q. How is M related to N?",
      "choices": {
        "a": "Nephew",
        "b": "Cousin",
        "c": "Data inadequate",
        "d": "None of these"
      },
      "correct": null,
      "has_figure": false,
      "skip_reason": null
    },
    {
      "number": 33,
      "passage_index": null,
      "seq_in_passage": null,
      "subject": "verbal",
      "topic_code": "blood_relations",
      "topic_name": "Blood Relations",
      "subtopic_code": "family_relationships",
      "subtopic_name": "Family Relationships",
      "body": "Kamal told Vimal, \" Yesterday I defeated the only brother of the daughter of my grandmother.\" Whom did Kamal defeated?",
      "choices": {
        "a": "Father",
        "b": "Son",
        "c": "Brother",
        "d": "Father-in-law"
      },
      "correct": null,
      "has_figure": false,
      "skip_reason": null
    },
    {
      "number": 34,
      "passage_index": null,
      "seq_in_passage": null,
      "subject": "verbal",
      "topic_code": "blood_relations",
      "topic_name": "Blood Relations",
      "subtopic_code": "family_relationships",
      "subtopic_name": "Family Relationships",
      "body": "A and B are brothers, C and D are sisters. A's son is D's brother, then how is B related to C?",
      "choices": {
        "a": "Father",
        "b": "Brother",
        "c": "Grandfather",
        "d": "Uncle"
      },
      "correct": null,
      "has_figure": false,
      "skip_reason": null
    },
    {
      "number": 35,
      "passage_index": null,
      "seq_in_passage": null,
      "subject": "verbal",
      "topic_code": "blood_relations",
      "topic_name": "Blood Relations",
      "subtopic_code": "family_relationships",
      "subtopic_name": "Family Relationships",
      "body": "Introducing Shyam, a lady said, 'The father of his father-in-law is my father-in-law'. How is Shyam related to the lady?",
      "choices": {
        "a": "Son",
        "b": "Husband",
        "c": "Son-in-law",
        "d": "Father"
      },
      "correct": null,
      "has_figure": false,
      "skip_reason": null
    },
    {
      "number": 36,
      "passage_index": null,
      "seq_in_passage": null,
      "subject": "verbal",
      "topic_code": "blood_relations",
      "topic_name": "Blood Relations",
      "subtopic_code": "family_relationships",
      "subtopic_name": "Family Relationships",
      "body": "D is the son- in-law of B, who is the brother-in-law of A, who is the brother of C. How is A related to B?",
      "choices": {
        "a": "Father",
        "b": "Son",
        "c": "Data inadequate",
        "d": "None of these"
      },
      "correct": null,
      "has_figure": false,
      "skip_reason": null
    },
    {
      "number": 37,
      "passage_index": null,
      "seq_in_passage": null,
      "subject": "verbal",
      "topic_code": "blood_relations",
      "topic_name": "Blood Relations",
      "subtopic_code": "family_relationships",
      "subtopic_name": "Family Relationships",
      "body": "Pointing to a lady, Chouhan said, 'She is the only daughter of my father-in-law's wife. How is this lady related to Chouhan?",
      "choices": {
        "a": "Mother",
        "b": "Wife",
        "c": "Cousin",
        "d": "Sister"
      },
      "correct": null,
      "has_figure": false,
      "skip_reason": null
    },
    {
      "number": 38,
      "passage_index": null,
      "seq_in_passage": null,
      "subject": "verbal",
      "topic_code": "blood_relations",
      "topic_name": "Blood Relations",
      "subtopic_code": "family_relationships",
      "subtopic_name": "Family Relationships",
      "body": "Pointing to a lady, Rishi said, 'This son of her brother is the brother of my wife'. How is this lady related to Rishi?",
      "choices": {
        "a": "Mother-in-law",
        "b": "Mother's sister",
        "c": "Sister of father-in-law",
        "d": "None of the above"
      },
      "correct": null,
      "has_figure": false,
      "skip_reason": null
    },
    {
      "number": 39,
      "passage_index": null,
      "seq_in_passage": null,
      "subject": "verbal",
      "topic_code": "blood_relations",
      "topic_name": "Blood Relations",
      "subtopic_code": "coded_relations",
      "subtopic_name": "Coded Relations",
      "body": "'S × T' means that S is the mother of T, 'S +T' means that S is the father of T, 'S –T' means that S is the sister of T. On the basis of this information, you have to select the option which shows that A is the grandfather of T?",
      "choices": {
        "a": "A + S + B – T",
        "b": "A × B + C – T",
        "c": "A + B – C × T",
        "d": "A – C + B × T"
      },
      "correct": null,
      "has_figure": false,
      "skip_reason": null
    },
    {
      "number": 40,
      "passage_index": null,
      "seq_in_passage": null,
      "subject": "verbal",
      "topic_code": "blood_relations",
      "topic_name": "Blood Relations",
      "subtopic_code": "family_relationships",
      "subtopic_name": "Family Relationships",
      "body": "Pointing towards a Boy Veena said \"He is the son of only son of my grandfather\". How is that boy related to Veena?",
      "choices": {
        "a": "Uncle",
        "b": "Brother",
        "c": "Cousin",
        "d": "Data inadequate"
      },
      "correct": null,
      "has_figure": false,
      "skip_reason": null
    },
    {
      "number": 41,
      "passage_index": null,
      "seq_in_passage": null,
      "subject": "verbal",
      "topic_code": "blood_relations",
      "topic_name": "Blood Relations",
      "subtopic_code": "family_relationships",
      "subtopic_name": "Family Relationships",
      "body": "P is the only son of Q who is the only daughter of S. D is the mother of B and daughter-in-law of Q. How is B related to Q?",
      "choices": {
        "a": "Grandson",
        "b": "Granddaughter",
        "c": "Son",
        "d": "Cannot be determined"
      },
      "correct": null,
      "has_figure": false,
      "skip_reason": null
    },
    {
      "number": 42,
      "passage_index": null,
      "seq_in_passage": null,
      "subject": "verbal",
      "topic_code": "blood_relations",
      "topic_name": "Blood Relations",
      "subtopic_code": "family_relationships",
      "subtopic_name": "Family Relationships",
      "body": "P's father is Q's son. M is the paternal uncle of P and N is the brother of Q. How is N related to M?",
      "choices": {
        "a": "Brother",
        "b": "Nephew",
        "c": "Cousin",
        "d": "None of these"
      },
      "correct": null,
      "has_figure": false,
      "skip_reason": null
    },
    {
      "number": 43,
      "passage_index": null,
      "seq_in_passage": null,
      "subject": "verbal",
      "topic_code": "blood_relations",
      "topic_name": "Blood Relations",
      "subtopic_code": "family_relationships",
      "subtopic_name": "Family Relationships",
      "body": "Daya has brother, Anil, Daya is the son of Chandra. Bimal is Chandra's father. In terms of relationship, what is Anil of Bimal?",
      "choices": {
        "a": "Son",
        "b": "Grandson",
        "c": "Brother",
        "d": "Grandfather"
      },
      "correct": null,
      "has_figure": false,
      "skip_reason": null
    },
    {
      "number": 44,
      "passage_index": 0,
      "seq_in_passage": 1,
      "subject": "verbal",
      "topic_code": "blood_relations",
      "topic_name": "Blood Relations",
      "subtopic_code": "family_relationships",
      "subtopic_name": "Family Relationships",
      "body": "Who is the brother-in-law of R?",
      "choices": {
        "a": "P",
        "b": "Z",
        "c": "Y",
        "d": "X"
      },
      "correct": null,
      "has_figure": false,
      "skip_reason": null
    },
    {
      "number": 45,
      "passage_index": 0,
      "seq_in_passage": 2,
      "subject": "verbal",
      "topic_code": "blood_relations",
      "topic_name": "Blood Relations",
      "subtopic_code": "family_relationships",
      "subtopic_name": "Family Relationships",
      "body": "How many female members are there in the family?",
      "choices": {
        "a": "One",
        "b": "Two",
        "c": "Three",
        "d": "Four"
      },
      "correct": null,
      "has_figure": false,
      "skip_reason": null
    },
    {
      "number": 46,
      "passage_index": 0,
      "seq_in_passage": 3,
      "subject": "verbal",
      "topic_code": "blood_relations",
      "topic_name": "Blood Relations",
      "subtopic_code": "family_relationships",
      "subtopic_name": "Family Relationships",
      "body": "Which of these is a pair of brothers?",
      "choices": {
        "a": "P and X",
        "b": "P and Z",
        "c": "Q and X",
        "d": "R and Y"
      },
      "correct": null,
      "has_figure": false,
      "skip_reason": null
    },
    {
      "number": 47,
      "passage_index": null,
      "seq_in_passage": null,
      "subject": "verbal",
      "topic_code": "blood_relations",
      "topic_name": "Blood Relations",
      "subtopic_code": "family_relationships",
      "subtopic_name": "Family Relationships",
      "body": "Mohan is the Son of Arun's father's sister. Prakash is the son of Reva, who is the mother of Vikas and grandmother of Arun. Pranab is the father of Neela and the grandfather of Mohan. Reva is the wife of Pranab. How is the wife of Vikas related to the lady?",
      "choices": {
        "a": "Sister",
        "b": "Sister-in-law",
        "c": "Niece",
        "d": "None of these"
      },
      "correct": null,
      "has_figure": false,
      "skip_reason": null
    }
  ],
  "solutions": [],
  "answers": [],
  "_page": 405
}