{
  "page_type": "questions",
  "chapter_number": null,
  "chapter_title": "Completion of Figures",
  "passages": [],
  "questions": [
    {
      "number": 36,
      "passage_index": null,
      "seq_in_passage": null,
      "subject": "non_verbal",
      "topic_code": "general",
      "topic_name": "Completion of Figures",
      "subtopic_code": "pattern_completion",
      "subtopic_name": "Pattern Completion",
      "body": "Complete the figure with the missing part.",
      "choices": {
        "a": "",
        "b": "",
        "c": "",
        "d": ""
      },
      "correct": null,
      "has_figure": true,
      "skip_reason": null
    },
    {
      "number": 37,
      "passage_index": null,
      "seq_in_passage": null,
      "subject": "non_verbal",
      "topic_code": "general",
      "topic_name": "Completion of Figures",
      "subtopic_code": "pattern_completion",
      "subtopic_name": "Pattern Completion",
      "body": "Complete the figure with the missing part.",
      "choices": {
        "a": "",
        "b": "",
        "c": "",
        "d": ""
      },
      "correct": null,
      "has_figure": true,
      "skip_reason": null
    },
    {
      "number": 38,
      "passage_index": null,
      "seq_in_passage": null,
      "subject": "non_verbal",
      "topic_code": "general",
      "topic_name": "Completion of Figures",
      "subtopic_code": "pattern_completion",
      "subtopic_name": "Pattern Completion",
      "body": "Complete the figure with the missing part.",
      "choices": {
        "a": "",
        "b": "",
        "c": "",
        "d": ""
      },
      "correct": null,
      "has_figure": true,
      "skip_reason": null
    },
    {
      "number": 39,
      "passage_index": null,
      "seq_in_passage": null,
      "subject": "non_verbal",
      "topic_code": "general",
      "topic_name": "Completion of Figures",
      "subtopic_code": "pattern_completion",
      "subtopic_name": "Pattern Completion",
      "body": "Complete the figure with the missing part.",
      "choices": {
        "a": "",
        "b": "",
        "c": "",
        "d": ""
      },
      "correct": null,
      "has_figure": true,
      "skip_reason": null
    },
    {
      "number": 40,
      "passage_index": null,
      "seq_in_passage": null,
      "subject": "non_verbal",
      "topic_code": "general",
      "topic_name": "Completion of Figures",
      "subtopic_code": "pattern_completion",
      "subtopic_name": "Pattern Completion",
      "body": "Complete the figure with the missing part.",
      "choices": {
        "a": "",
        "b": "",
        "c": "",
        "d": ""
      },
      "correct": null,
      "has_figure": true,
      "skip_reason": null
    },
    {
      "number": 41,
      "passage_index": null,
      "seq_in_passage": null,
      "subject": "non_verbal",
      "topic_code": "general",
      "topic_name": "Completion of Figures",
      "subtopic_code": "pattern_completion",
      "subtopic_name": "Pattern Completion",
      "body": "Complete the figure with the missing part.",
      "choices": {
        "a": "",
        "b": "",
        "c": "",
        "d": ""
      },
      "correct": null,
      "has_figure": true,
      "skip_reason": null
    },
    {
      "number": 42,
      "passage_index": null,
      "seq_in_passage": null,
      "subject": "non_verbal",
      "topic_code": "general",
      "topic_name": "Completion of Figures",
      "subtopic_code": "pattern_completion",
      "subtopic_name": "Pattern Completion",
      "body": "Complete the figure with the missing part.",
      "choices": {
        "a": "",
        "b": "",
        "c": "",
        "d": ""
      },
      "correct": null,
      "has_figure": true,
      "skip_reason": null
    },
    {
      "number": 43,
      "passage_index": null,
      "seq_in_passage": null,
      "subject": "non_verbal",
      "topic_code": "general",
      "topic_name": "Completion of Figures",
      "subtopic_code": "pattern_completion",
      "subtopic_name": "Pattern Completion",
      "body": "Complete the figure with the missing part.",
      "choices": {
        "a": "",
        "b": "",
        "c": "",
        "d": ""
      },
      "correct": null,
      "has_figure": true,
      "skip_reason": null
    },
    {
      "number": 44,
      "passage_index": null,
      "seq_in_passage": null,
      "subject": "non_verbal",
      "topic_code": "general",
      "topic_name": "Completion of Figures",
      "subtopic_code": "pattern_completion",
      "subtopic_name": "Pattern Completion",
      "body": "Complete the figure with the missing part.",
      "choices": {
        "a": "",
        "b": "",
        "c": "",
        "d": ""
      },
      "correct": null,
      "has_figure": true,
      "skip_reason": null
    },
    {
      "number": 45,
      "passage_index": null,
      "seq_in_passage": null,
      "subject": "non_verbal",
      "topic_code": "general",
      "topic_name": "Completion of Figures",
      "subtopic_code": "pattern_completion",
      "subtopic_name": "Pattern Completion",
      "body": "Complete the figure with the missing part.",
      "choices": {
        "a": "",
        "b": "",
        "c": "",
        "d": ""
      },
      "correct": null,
      "has_figure": true,
      "skip_reason": null
    },
    {
      "number": 46,
      "passage_index": null,
      "seq_in_passage": null,
      "subject": "non_verbal",
      "topic_code": "general",
      "topic_name": "Completion of Figures",
      "subtopic_code": "pattern_completion",
      "subtopic_name": "Pattern Completion",
      "body": "Complete the figure with the missing part.",
      "choices": {
        "a": "",
        "b": "",
        "c": "",
        "d": ""
      },
      "correct": null,
      "has_figure": true,
      "skip_reason": null
    },
    {
      "number": 47,
      "passage_index": null,
      "seq_in_passage": null,
      "subject": "non_verbal",
      "topic_code": "general",
      "topic_name": "Completion of Figures",
      "subtopic_code": "pattern_completion",
      "subtopic_name": "Pattern Completion",
      "body": "Complete the figure with the missing part.",
      "choices": {
        "a": "",
        "b": "",
        "c": "",
        "d": ""
      },
      "correct": null,
      "has_figure": true,
      "skip_reason": null
    },
    {
      "number": 48,
      "passage_index": null,
      "seq_in_passage": null,
      "subject": "non_verbal",
      "topic_code": "general",
      "topic_name": "Completion of Figures",
      "subtopic_code": "pattern_completion",
      "subtopic_name": "Pattern Completion",
      "body": "Complete the figure with the missing part.",
      "choices": {
        "a": "",
        "b": "",
        "c": "",
        "d": ""
      },
      "correct": null,
      "has_figure": true,
      "skip_reason": null
    }
  ],
  "solutions": [],
  "answers": [],
  "_page": 854
}