{
  "page_type": "questions",
  "chapter_number": null,
  "chapter_title": "Completion of Figures",
  "passages": [],
  "questions": [
    {
      "number": 49,
      "passage_index": null,
      "seq_in_passage": null,
      "subject": "non_verbal",
      "topic_code": "general",
      "topic_name": "Completion of Figures",
      "subtopic_code": "pattern_completion",
      "subtopic_name": "Pattern Completion",
      "body": "All the four parts are similar except for a diagonal line passing through the parts (2) and (3). Also, each part comprises of a quarter circle in such a way that there is a semi-circle on a pair of opposite sides of the question figure. Clearly, answer figure (b) completes the pattern.",
      "choices": {
        "a": "...",
        "b": "...",
        "c": "...",
        "d": "..."
      },
      "correct": "b",
      "has_figure": true,
      "skip_reason": null
    },
    {
      "number": 50,
      "passage_index": null,
      "seq_in_passage": null,
      "subject": "non_verbal",
      "topic_code": "general",
      "topic_name": "Completion of Figures",
      "subtopic_code": "pattern_completion",
      "subtopic_name": "Pattern Completion",
      "body": "Here, the upper two adjacent parts i.e., (1) and (2) have designs which are laterally inverted forms of each other. Then, the design in missing part i.e., (4) will be the laterally inverted form of the design in part (3). So, from the answer options given it is clear that design given, in option (c) is the correct laterally inverted form of (3) and it will replace the (?) to complete the pattern.",
      "choices": {
        "a": "...",
        "b": "...",
        "c": "...",
        "d": "..."
      },
      "correct": "c",
      "has_figure": true,
      "skip_reason": null
    },
    {
      "number": 51,
      "passage_index": null,
      "seq_in_passage": null,
      "subject": "non_verbal",
      "topic_code": "general",
      "topic_name": "Completion of Figures",
      "subtopic_code": "pattern_completion",
      "subtopic_name": "Pattern Completion",
      "body": "Here, all the three equal parts have similar design. So, we can obtain the answer figure for the missing portion by rotating the question figure by 90° clockwise. Now, it is clear that answer figure (d) completes the question figure.",
      "choices": {
        "a": "...",
        "b": "...",
        "c": "...",
        "d": "..."
      },
      "correct": "d",
      "has_figure": true,
      "skip_reason": null
    },
    {
      "number": 52,
      "passage_index": null,
      "seq_in_passage": null,
      "subject": "non_verbal",
      "topic_code": "general",
      "topic_name": "Completion of Figures",
      "subtopic_code": "pattern_completion",
      "subtopic_name": "Pattern Completion",
      "body": "Here, the upper two adjacent parts i.e., (1) and (2) have designs which are laterally inverted forms of each other. Then, the design in missing part i.e., (4) will be the laterally inverted form of the design in part (4). So, from the answer options given it is clear that design given in option (d) is the correct laterally inverted form of (3) and it will replace the (?) to complete the pattern.",
      "choices": {
        "a": "...",
        "b": "...",
        "c": "...",
        "d": "..."
      },
      "correct": "d",
      "has_figure": true,
      "skip_reason": null
    },
    {
      "number": 53,
      "passage_index": null,
      "seq_in_passage": null,
      "subject": "non_verbal",
      "topic_code": "general",
      "topic_name": "Completion of Figures",
      "subtopic_code": "pattern_completion",
      "subtopic_name": "Pattern Completion",
      "body": "Here, the upper two adjacent parts i.e., (1) and (2) have designs which are laterally inverted forms of each other. Then, the design in missing part i.e., (4) will be the laterally inverted form of the design in part (4). So, from the answer options given, it is clear that design given in option (a) is the correct laterally inverted form of (3) and it will replace the (?) to complete the pattern.",
      "choices": {
        "a": "...",
        "b": "...",
        "c": "...",
        "d": "..."
      },
      "correct": "a",
      "has_figure": true,
      "skip_reason": null
    },
    {
      "number": 54,
      "passage_index": null,
      "seq_in_passage": null,
      "subject": "non_verbal",
      "topic_code": "general",
      "topic_name": "Completion of Figures",
      "subtopic_code": "pattern_completion",
      "subtopic_name": "Pattern Completion",
      "body": "Here, the lower two adjacent parts i.e., (3) and (4) have designs which are laterally inverted form of each other. Then, the design in missing part i.e., (1) will be the laterally inverted form of the design in part (2). So, from the answer options given, it is clear that design given in option (a) is the correct laterally inverted form of (2) and it will replace the (?) to complete the pattern.",
      "choices": {
        "a": "...",
        "b": "...",
        "c": "...",
        "d": "..."
      },
      "correct": "a",
      "has_figure": true,
      "skip_reason": null
    },
    {
      "number": 55,
      "passage_index": null,
      "seq_in_passage": null,
      "subject": "non_verbal",
      "topic_code": "general",
      "topic_name": "Completion of Figures",
      "subtopic_code": "pattern_completion",
      "subtopic_name": "Pattern Completion",
      "body": "Here, all the three equal parts have similar design. So, we can obtain the answer figure for the missing portion by rotating the question figure by 90° clockwise. Now, it is clear that answer figure (a) completes the question figure.",
      "choices": {
        "a": "...",
        "b": "...",
        "c": "...",
        "d": "..."
      },
      "correct": "a",
      "has_figure": true,
      "skip_reason": null
    },
    {
      "number": 56,
      "passage_index": null,
      "seq_in_passage": null,
      "subject": "non_verbal",
      "topic_code": "general",
      "topic_name": "Completion of Figures",
      "subtopic_code": "pattern_completion",
      "subtopic_name": "Pattern Completion",
      "body": "Here, the upper two adjacent parts i.e., (1) and (2) have designs which are laterally inverted forms of each other. Then, the design in missing part i.e., (4) will be the laterally inverted form of the design in part (3). So from the answer options given it is clear that design given in option (b) is the correct laterally inverted form of (3) and it will replace the (?) to complete the pattern.",
      "choices": {
        "a": "...",
        "b": "...",
        "c": "...",
        "d": "..."
      },
      "correct": "b",
      "has_figure": true,
      "skip_reason": null
    },
    {
      "number": 57,
      "passage_index": null,
      "seq_in_passage": null,
      "subject": "non_verbal",
      "topic_code": "general",
      "topic_name": "Completion of Figures",
      "subtopic_code": "pattern_completion",
      "subtopic_name": "Pattern Completion",
      "body": "Here, the lower two adjacent parts i.e., (3) and (4) have designs which are laterally inverted forms of each other. Then, the design in missing part i.e., (2) will be the laterally inverted form of the design in part (1). So, from the answer options given it is clear that design given in option (c) is the correct laterally inverted form of (1) and it will replace the (?) to complete the pattern.",
      "choices": {
        "a": "...",
        "b": "...",
        "c": "...",
        "d": "..."
      },
      "correct": "c",
      "has_figure": true,
      "skip_reason": null
    },
    {
      "number": 58,
      "passage_index": null,
      "seq_in_passage": null,
      "subject": "non_verbal",
      "topic_code": "general",
      "topic_name": "Completion of Figures",
      "subtopic_code": "pattern_completion",
      "subtopic_name": "Pattern Completion",
      "body": "Here, the upper two adjacent parts i.e., (1) and (2) have designs which are laterally inverted forms of each other. Then, the design in missing part i.e., (3) will be the laterally inverted form of the design in part (4). So, from the answer options given it is clear that design given in option (b) is the correct laterally inverted form of (4) and it will replace the (?) to complete the pattern.",
      "choices": {
        "a": "...",
        "b": "...",
        "c": "...",
        "d": "..."
      },
      "correct": "b",
      "has_figure": true,
      "skip_reason": null
    },
    {
      "number": 59,
      "passage_index": null,
      "seq_in_passage": null,
      "subject": "non_verbal",
      "topic_code": "general",
      "topic_name": "Completion of Figures",
      "subtopic_code": "pattern_completion",
      "subtopic_name": "Pattern Completion",
      "body": "Here, the upper two adjacent parts i.e., (1) and (2) have designs which are laterally inverted forms of each other. Then, the design in missing part i.e., (3) will be the laterally inverted form of the design in part (4). So, from the answer options given it is clear that design given in option (d) is the correct laterally inverted form of (4) and it will replace the (?) to complete the pattern.",
      "choices": {
        "a": "...",
        "b": "...",
        "c": "...",
        "d": "..."
      },
      "correct": "d",
      "has_figure": true,
      "skip_reason": null
    },
    {
      "number": 60,
      "passage_index": null,
      "seq_in_passage": null,
      "subject": "non_verbal",
      "topic_code": "general",
      "topic_name": "Completion of Figures",
      "subtopic_code": "pattern_completion",
      "subtopic_name": "Pattern Completion",
      "body": "Here, by analysis we can observe that the given pattern is of a triangle. So, it is clear that option (a) will replace the (?) to make the question figure complete as shown in the adjacent figure.",
      "choices": {
        "a": "...",
        "b": "...",
        "c": "...",
        "d": "..."
      },
      "correct": "a",
      "has_figure": true,
      "skip_reason": null
    },
    {
      "number": 61,
      "passage_index": null,
      "seq_in_passage": null,
      "subject": "non_verbal",
      "topic_code": "general",
      "topic_name": "Completion of Figures",
      "subtopic_code": "pattern_completion",
      "subtopic_name": "Pattern Completion",
      "body": "Here, figure (4) is obtained by 90° anti-clockwise rotation of figure (1). Similarly, figure (3) can be obtained by 90° anti-clockwise rotation of figure (2). So, it is clear that option (d) will replace the (?) to make the question figure complete.",
      "choices": {
        "a": "...",
        "b": "...",
        "c": "...",
        "d": "..."
      },
      "correct": "d",
      "has_figure": true,
      "skip_reason": null
    },
    {
      "number": 62,
      "passage_index": null,
      "seq_in_passage": null,
      "subject": "non_verbal",
      "topic_code": "general",
      "topic_name": "Completion of Figures",
      "subtopic_code": "pattern_completion",
      "subtopic_name": "Pattern Completion",
      "body": "From (1) to (2), the upper and the lower element get vertically inverted and swap places. Likewise, the left and right elements also interchange their respective positions. So, the missing figure i.e., (4) is obtained from (3) in a similar fashion.",
      "choices": {
        "a": "...",
        "b": "...",
        "c": "...",
        "d": "..."
      },
      "correct": "c",
      "has_figure": true,
      "skip_reason": null
    },
    {
      "number": 63,
      "passage_index": null,
      "seq_in_passage": null,
      "subject": "non_verbal",
      "topic_code": "general",
      "topic_name": "Completion of Figures",
      "subtopic_code": "pattern_completion",
      "subtopic_name": "Pattern Completion",
      "body": "Here, by analysis we can observe that the given pattern is of two intersecting triangles inside the squares. So, it is clear that option (d) will replace the (?) to make the figure complete as shown in the below figure.",
      "choices": {
        "a": "...",
        "b": "...",
        "c": "...",
        "d": "..."
      },
      "correct": "d",
      "has_figure": true,
      "skip_reason": null
    },
    {
      "number": 64,
      "passage_index": null,
      "seq_in_passage": null,
      "subject": "non_verbal",
      "topic_code": "general",
      "topic_name": "Completion of Figures",
      "subtopic_code": "pattern_completion",
      "subtopic_name": "Pattern Completion",
      "body": "Here, by analysis we can find that only option (a) will replace the (?) to complete the design pattern of the figure.",
      "choices": {
        "a": "...",
        "b": "...",
        "c": "...",
        "d": "..."
      },
      "correct": "a",
      "has_figure": true,
      "skip_reason": null
    }
  ],
  "solutions": [],
  "answers": [],
  "_page": 860
}